labjack_unified/__init__.py
labjack_unified/devices.py
labjack_unified/utils.py
labjack_unified-0.0.5.dist-info/LICENSE.txt
labjack_unified-0.0.5.dist-info/METADATA
labjack_unified-0.0.5.dist-info/WHEEL
labjack_unified-0.0.5.dist-info/top_level.txt
labjack_unified-0.0.5.dist-info/RECORD
