Metadata-Version: 2.1
Name: labjack-unified
Version: 0.0.5
Summary: Unified methods for LabJacks U3, U6, and T7
Home-page: https://github.com/EduardoNigro/labjack-unified
Author: Eduardo Nigro
Author-email: eduardo.b.nigro@gmail.com
License: UNKNOWN
Project-URL: Bug Tracker, https://github.com/EduardoNigro/labjack-unified/issues
Platform: UNKNOWN
Classifier: Programming Language :: Python :: 3
Classifier: License :: OSI Approved :: MIT License
Classifier: Operating System :: Microsoft :: Windows :: Windows 10
Requires-Python: >=3.6
License-File: LICENSE.txt
Requires-Dist: LabJackPython
Requires-Dist: labjack-ljm
Requires-Dist: plotly
Requires-Dist: numpy
Requires-Dist: scipy
